pyhartig/__init__.py
pyhartig/algebra/Terms.py
pyhartig/algebra/Tuple.py
pyhartig/algebra/__init__.py
pyhartig/expressions/Constant.py
pyhartig/expressions/Expression.py
pyhartig/expressions/FunctionCall.py
pyhartig/expressions/Reference.py
pyhartig/expressions/__init__.py
pyhartig/functions/__init__.py
pyhartig/functions/builtins.py
pyhartig/mapping/MappingParser.py
pyhartig/mapping/__init__.py
pyhartig/operators/EquiJoinOperator.py
pyhartig/operators/ExtendOperator.py
pyhartig/operators/Operator.py
pyhartig/operators/ProjectOperator.py
pyhartig/operators/SourceOperator.py
pyhartig/operators/UnionOperator.py
pyhartig/operators/__init__.py
pyhartig/operators/sources/JsonSourceOperator.py
pyhartig/operators/sources/__init__.py
pyhartig-0.2.1.dist-info/licenses/LICENSE
pyhartig-0.2.1.dist-info/METADATA
pyhartig-0.2.1.dist-info/WHEEL
pyhartig-0.2.1.dist-info/top_level.txt
pyhartig-0.2.1.dist-info/RECORD
