Metadata-Version: 2.4
Name: pyhartig
Version: 0.2.1
Summary: A Python implementation of Olaf Hartig's algebra for Knowledge Graph Construction. Developed for the 'Engineering For Research I' course (M1 SMART Computing) at Nantes Université (LS2N - GDD Team).
Author-email: Anthony MUDET <anthony.mudet@etu.univ-nantes.fr>, Léo FERMÉ <leo.ferme@etu.univ-nantes.fr>, Mohamed Lamine MERAH <mohamed.merah@etu.univ-nantes.fr>
Project-URL: Homepage, https://github.com/Armotik/pyhartig
Project-URL: Repository, https://github.com/Armotik/pyhartig
Project-URL: Theoretical-Foundation, https://arxiv.org/abs/2503.10385
Keywords: SPARQL,Algebra,Olaf Hartig,Query Processing,Knowledge Graph Construction,Semantic Web,LS2N,Nantes Universite
Classifier: Programming Language :: Python :: 3
Classifier: License :: OSI Approved :: MIT License
Classifier: Operating System :: OS Independent
License-File: LICENSE
Requires-Dist: jsonpath-ng>=1.7.0
Requires-Dist: rdflib>=6.0.0
Provides-Extra: test
Requires-Dist: pytest>=7.0; extra == "test"
Dynamic: license-file
